thalentfrx-0.1.12.dist-info/METADATA
thalentfrx-0.1.12.dist-info/WHEEL
thalentfrx-0.1.12.dist-info/entry_points.txt
thalentfrx-0.1.12.dist-info/licenses/LICENSE
thalentfrx/__init__.py
thalentfrx/applications.py
thalentfrx/configs/Database.py
thalentfrx/configs/Environment.py
thalentfrx/configs/Logger.py
thalentfrx/configs/__init__.py
thalentfrx/core/__init__.py
thalentfrx/core/endpoint/__init__.py
thalentfrx/core/endpoint/restapi/AuthRouter.py
thalentfrx/core/endpoint/restapi/AuthSchema.py
thalentfrx/core/endpoint/restapi/CommonSchema.py
thalentfrx/core/endpoint/restapi/__init__.py
thalentfrx/core/entities/BaseEntity.py
thalentfrx/core/entities/Filter.py
thalentfrx/core/entities/ListParam.py
thalentfrx/core/entities/PageRecord.py
thalentfrx/core/entities/PagingParam.py
thalentfrx/core/entities/Sort.py
thalentfrx/core/entities/__init__.py
thalentfrx/core/injector/InjectorModule.py
thalentfrx/core/injector/__init__.py
thalentfrx/core/models/AuditMixinModel.py
thalentfrx/core/models/BaseModel.py
thalentfrx/core/models/Helpers.py
thalentfrx/core/models/__init__.py
thalentfrx/core/repositories/AsyncBaseRepository.py
thalentfrx/core/repositories/BaseRepository.py
thalentfrx/core/repositories/Helpers.py
thalentfrx/core/repositories/__init__.py
thalentfrx/core/services/AsyncBaseService.py
thalentfrx/core/services/AuthBaseService.py
thalentfrx/core/services/AuthDto.py
thalentfrx/core/services/BaseDto.py
thalentfrx/core/services/BaseService.py
thalentfrx/core/services/__init__.py
thalentfrx/db/__init__.py
thalentfrx/db/async_session_manager.py
thalentfrx/db/session_manager.py
thalentfrx/helpers/Container.py
thalentfrx/helpers/SetupVersion.json
thalentfrx/helpers/SetupVersion.py
thalentfrx/helpers/StartUpInfo.py
thalentfrx/helpers/__init__.py
thalentfrx/helpers/fastapi/AppExceptions.py
thalentfrx/helpers/fastapi/AuthHelper.py
thalentfrx/helpers/fastapi/ExceptionHandlers.py
thalentfrx/helpers/fastapi/__init__.py
thalentfrx/testclient.py
thalentfrx-0.1.12.dist-info/RECORD
